yasuo/__init__.py
yasuo-3.0.1.dist-info/LICENSE
yasuo-3.0.1.dist-info/METADATA
yasuo-3.0.1.dist-info/WHEEL
yasuo-3.0.1.dist-info/top_level.txt
yasuo-3.0.1.dist-info/RECORD
