Metadata-Version: 2.1
Name: yasuo
Version: 3.0.1
Summary: A Yasuo Python package
Home-page: https://github.com/puffer-python/yasuo
Author: Dung BV
Author-email: bvdzung@gmail.com
License: MIT License
Keywords: yasuo,python,vietnamese
Platform: Linux (x86, x86_64, ARMv6, ARMv7, ARMv8)
Platform: Windows (32-bit, 64-bit)
Platform: macOS (x86_64)
Classifier: Programming Language :: Python :: 3
Classifier: License :: OSI Approved :: MIT License
Classifier: Operating System :: OS Independent
Requires-Dist: pytz
Requires-Dist: slugify
Requires-Dist: unidecode
